{"vt1":[{"name":["Standing LP","LP"],"frame":["4","2","7","5","3","4","2","S CA V","30","70","0 / 20","High","","",""]},{"name":["Standing MP","MP"],"frame":["5","4","13","2","0","11","9","S CA V","70","100","0 / 30","High","","",""]},{"name":["Standing HP","HP"],"frame":["12","2","19","0","-3","7","4","CA V","80","150","0 / 50","High","","","Triggers Crush Counter (D)"]},{"name":["Standing LK","LK"],"frame":["3","2","8","2","1","4","3","V","30","70","0 / 20","High","","",""]},{"name":["Standing MK","MK"],"frame":["6","3","12","5","2","12","9","S CA V","60","100","0 / 30","High","","",""]},{"name":["Standing HK","HK"],"frame":["9","3","18","7","3","15","11","V","80","150","0 / 50","High","","","Triggers Crush Counter (+23F)"]},{"name":["Crouching LP","(WHILE CROUCHING)","LP"],"frame":["4","3","7","4","3","5","4","S CA V","30","70","0 / 20","High","","","Can be rapid canceled"]},{"name":["Crouching MP","(WHILE CROUCHING)","MP"],"frame":["6","3","12","4","2","11","9","S CA V","60","100","0 / 30","High","","",""]},{"name":["Crouching HP","(WHILE CROUCHING)","HP"],"frame":["8","5","22","-1","-5","11","7","S CA V","90\n(*80)","150","0 / 50","High","","","*"]},{"name":["Crouching LK","(WHILE CROUCHING)","LK"],"frame":["4","3","8","4","1","7","4","V","20","70","0 / 20","Low","","",""]},{"name":["Crouching MK","(WHILE CROUCHING)","MK"],"frame":["7","2","17","2","-2","13","9","V","60","100","0 / 30","Low","","",""]},{"name":["Crouching HK","(WHILE CROUCHING)","HK"],"frame":["8","2","26","D","-14","D","6","V","100","150","0 / 50","Low","","","Triggers Crush Counter (D)"]},{"name":["Jumping LP","(DURING JUMP)","LP"],"frame":["4","6","","","","","","","40","70","0 / 20","Mid","","",""]},{"name":["Jumping MP","(DURING JUMP)","MP"],"frame":["5","3","","","","","","","70","100","0 / 30","Mid","","",""]},{"name":["Jumping HP","(DURING JUMP)","HP"],"frame":["7","4","","","","","","","90","150","0 / 50","Mid","","",""]},{"name":["Jumping LK","(DURING JUMP)","LK"],"frame":["3","5","","","","","","","40","70","0 / 20","Mid","","",""]},{"name":["Jumping MK","(DURING JUMP)","MK"],"frame":["6","5","","","","","","","70","100","0 / 30","Mid","","",""]},{"name":["Jumping HK","(DURING JUMP)","HK"],"frame":["9","4","","","","","","","90","150","0 / 50","Mid","","",""]},{"name":["Hard Smasher (2)","MK",".","MP"],"frame":["6","4","20","D","-8","D","7","V","40","80","0 / 40","High","","",""]},{"name":["Hard Smasher (3)","(WHEN SELECTING VSKILL I)","MK",".","MP",".","MP","MK"],"frame":["","","31 total frames","","","","","","","","","","","",""]},{"name":["Hard Smasher (4)","(WHEN SELECTING VSKILL I)","MK",".","MP",".","MP","MK",".","P"],"frame":["21","2","23","D","-8","D","9","V","60","120","V-Gauge 0 / 125","High","","",""]},{"name":["Hard Pressure (4)","(WHEN SELECTING VSKILL I)","MK",".","MP",".","MP","MK",".","K"],"frame":["26","3","21","D","-8","D","8","V","60","120","V-Gauge 0 / 125","Mid","","",""]},{"name":["OTB","(WHEN SELECTING VSKILL II)","MK",".","MP",".","MP","MK"],"frame":["","","50 total frames","","","","","","","","","","","",""]},{"name":["Under Impact (2)","LK",".","MK"],"frame":["6","3","16","1","-7","12","4","V","40","70","0 / 40","High","","",""]},{"name":["Under Impact (3)","LK",".","MK",".","HK"],"frame":["9","2","21","D","-8","D","7","V","70","100","0 / 60","High","","",""]},{"name":["Stomping Combo (2)","(WHILE CROUCHING)","MK",".","2","+","MK"],"frame":["9","2","20","2","-7","7","-2","V","40","80","0 / 40","Low","","","Forces stand"]},{"name":["Dirty Bomber","(NEAR OPPONENT)","6","OR","5","+","LP","LK"],"frame":["5","3","17","D","","","","","140","150","0 / 70","Throw","","",""]},{"name":["Dirty Shot","(NEAR OPPONENT)","4","+","LP","LK"],"frame":["5","3","17","D","","","","","130","200","0 / 100","Throw","","",""]},{"name":["[VS1] KKB","(WHEN SELECTING VSKILL I)","MP","MK"],"frame":["","","29 total frames","","","","","","","","","","","","4F - 22F projectile invincibility"]},{"name":["[VS1] KKB (Cancel)","(WHEN SELECTING VSKILL I)","MP","MK"],"frame":["","","25 total frames","","","","","","","","","","","","4F - 22F projectile invincibility"]},{"name":["[VS1] Buffalo Swing","(WHEN SELECTING VSKILL I)","(DURING KKB)","P"],"frame":["7","2","21","2","-4","17","11","V","60","100","V-Gauge 0 / 80","High","","","1F - 5F projectile invincibility"]},{"name":["[VS1] Buffalo Pressure","(WHEN SELECTING VSKILL I)","(DURING KKB)","K"],"frame":["17","3","19","5","-7","19","8","V","50","100","V-Gauge 0 / 100","Mid","","","1F - 14F projectile invincibility"]},{"name":["[VS2] FFB","(WHEN SELECTING VSKILL II)","MP","MK"],"frame":["","","50 total frames","","","","","","","","","","","","発動後一回だけダッシュストレート・チャージングバッファローの性質変化\n（VT1中のラッシュ時はすべてのストレートが強化される）"]},{"name":["Crazy Rush","HP","HK"],"frame":["1","","6","","","","","","","","V-Gauge -900 / 0","","","","V-Gauge Timer + 2000F\nWhile active, Balrog gains the special moves Charging Buffalo and Bursting Buffalo"]},{"name":["Buffalo Headbutt","(DURING GUARD)","6","+","LP","M","H"],"frame":["17","3","23","D","-2","","","","60","0","V-Gauge -300 / 0","High","","18F - 31F","1F - 30F attack & projectile invincibility\nRecover 200 stun upon activation"]},{"name":["L Dash Straight","c4","6","+","LP"],"frame":["*","4","22","2","-4","5","-1","CA V VS*","80","150","10 / 20","High","","","* VS* VS*"]},{"name":["M Dash Straight","c4","6","+","MP"],"frame":["*","4","22","3","-6","6","-3","CA V VS*","90","150","10 / 20","High","","","* VS* VS*"]},{"name":["H Dash Straight","c4","6","+","HP"],"frame":["*","4","22","2","-7","6","-3","CA V VS*","100","150","10 / 20","High","","","* VS* VS*"]},{"name":["L Dash Straight (VS2 Ver.)","(DURING V-SKILL II)","c4","6","+","LP"],"frame":["*","4","22","D","2","D","5","CA V","90","100","V-Gauge 20 / 40\n10 / 20","High","","","*"]},{"name":["M Dash Straight (VS2 Ver.)","(DURING V-SKILL II)","c4","6","+","MP"],"frame":["*","4","22","D","2","D","5","CA V","100","100","V-Gauge 20 / 40\n10 / 20","High","","","*"]},{"name":["H Dash Straight (VS2 Ver.)","(DURING V-SKILL II)","c4","6","+","HP"],"frame":["*","4","22","D","2","D","6","CA V","110","100","V-Gauge 20 / 40\n10 / 20","High","","","*"]},{"name":["EX Dash Straight","c4","6","+","P","P"],"frame":["*","6","29","D","1","8/D","4","V VS*","150","200","-300 / 0","High","","","* VS* VS*"]},{"name":["EX Dash Straight (VS2 Ver.)","(DURING V-SKILL II)","c4","6","+","P","P"],"frame":["*","6","29","D","4","10/D","5","V","160","120","V-Gauge 20 / 60\n-300 / 0","High","","","*"]},{"name":["[VT] Charging Buffalo (1)","(DURING V-TRIGGER WITH SPECIAL MOVE)","6","+","P"],"frame":["12","6","17","2","-2","","","CA VS*","30","100","0 / 20","High","","","VS*"]},{"name":["[VT] Charging Buffalo (2)","(DURING CHARGING BUFFALO OR BURSTING BUFFALO)","6","+","P"],"frame":["12","6","16","2","-2","","","CA VS*","40","100","0 / 20","High","","","VS*"]},{"name":["[VT] Charging Buffalo (3)","(DURING CHARGING BUFFALO OR BURSTING BUFFALO)","6","+","P"],"frame":["12","6","15","2","-2","","","CA VS*","50","100","0 / 20","High","","","VS*"]},{"name":["[VT] Charging Buffalo (4)","(DURING CHARGING BUFFALO OR BURSTING BUFFALO)","6","+","P"],"frame":["17","6","29","D","-13","","","CA","90","100","0 / 40","High","","","Uses 300F V-Gauge Timer"]},{"name":["[VT] EX Charging Buffalo","(DURING V-TRIGGER WITH SPECIAL EX MOVE)","6","+","P"],"frame":["11","6","18","D","-2","","","VS*","70","100","","High","","","VS* VS*"]},{"name":["[VT] Charging Buffalo (VS2 Ver.) (1)","(DURING V-SKILL II)","(DURING V-TRIGGER WITH SPECIAL MOVE)","6","+","P"],"frame":["12","6","17","D","0","","","CA","60","80","0 / 20","High","","","Uses 500F V-Gauge Timer"]},{"name":["[VT] Charging Buffalo (VS2 Ver.) (2)","(DURING V-SKILL II)","(DURING CHARGING BUFFALO OR BURSTING BUFFALO)","6","+","P"],"frame":["12","6","16","D","1","","","CA","60","80","0 / 20","High","","","Uses 300F V-Gauge Timer"]},{"name":["[VT] Charging Buffalo (VS2 Ver.) (3)","(DURING V-SKILL II)","(DURING CHARGING BUFFALO OR BURSTING BUFFALO)","6","+","P"],"frame":["12","6","15","D","2","","","CA","70","80","0 / 20","High","","","Uses 300F V-Gauge Timer"]},{"name":["[VT] Charging Buffalo (VS2 Ver.) (4)","(DURING V-SKILL II)","(DURING CHARGING BUFFALO OR BURSTING BUFFALO)","6","+","P"],"frame":["17","6","29","D","-12","","","CA","130","190","0 / 40","High","","","Uses 300F V-Gauge Timer"]},{"name":["[VT] EX Charging Buffalo (VS2 Ver.) (1)","(DURING V-SKILL II)","(DURING V-TRIGGER WITH SPECIAL EX MOVE)","6","+","P"],"frame":["11","6","18","D","-1","","","","70","100","","High","","","Uses 500F V-Gauge Timer"]},{"name":["[VT] EX Charging Buffalo (VS2 Ver.) (2)","(DURING V-SKILL II)","(DURING V-TRIGGER WITH SPECIAL EX MOVE)","6","+","P"],"frame":["11","6","18","D","-1","","","","70","120","","High","","","Uses 500F V-Gauge Timer"]},{"name":["L Dash Grand Blow","c4","6","+","LK"],"frame":["17","2","26","D","-7","D","3","V VS*","70","150","20 / 40","Low","","","* VS* VS*"]},{"name":["M Dash Grand Blow","c4","6","+","MK"],"frame":["*","2","26","D","-7","D","3","V VS*","80","150","20 / 40","Low","","","* VS* VS*"]},{"name":["H Dash Grand Blow","c4","6","+","HK"],"frame":["*","2","26","D","-7","D","3","V VS*","90","150","20 / 40","Low","","","* VS* VS*"]},{"name":["EX Dash Grand Blow","c4","6","+","K","K"],"frame":["*","2","23","D","-2","D","5","V VS*","140","200","-300 / 0","Low","","","* VS* VS*"]},{"name":["L Screw Smash","623","+","LK"],"frame":["10","5","25","D","-10","D","12","CA V","100","150","20 / 40","High","","","Will not hit crouching opponents"]},{"name":["M Screw Smash","623","+","MK"],"frame":["13","5","26","D","-10","D","13","CA V","100","150","20 / 40","High","","","Will not hit crouching opponents"]},{"name":["H Screw Smash","623","+","HK"],"frame":["23","5","23","D","-10","D","10","CA V","100","150","20 / 40","High","","","Will not hit crouching opponents"]},{"name":["EX Screw Smash","623","+","K","K"],"frame":["12","5","29","D","-17","D","-7","V","160","200","-300 / 0","High","","","Armor from 3F to 16F"]},{"name":["[VT] Bursting Buffalo (1)","(DURING V-TRIGGER WITH SPECIAL MOVE)","6","+","K"],"frame":["14","5","21","D","-2","","","CA VS*","40","50","0 / 20","High","","","VS*"]},{"name":["[VT] Bursting Buffalo (2)","(DURING CHARGING BUFFALO OR BURSTING BUFFALO)","6","+","K"],"frame":["14","5","21","D","-2","","","CA VS*","50","50","0 / 20","High","","","VS*"]},{"name":["[VT] Bursting Buffalo (3)","(DURING CHARGING BUFFALO OR BURSTING BUFFALO)","6","+","K"],"frame":["14","5","21","D","-2","","","CA VS*","60","50","0 / 20","High","","","VS*"]},{"name":["[VT] Bursting Buffalo (4)","(DURING CHARGING BUFFALO OR BURSTING BUFFALO)","6","+","K"],"frame":["17","5","38","D","-21","","","","100","50","0 / 40","High","","","Uses 300F V-Gauge Timer"]},{"name":["[VT] EX Bursting Buffalo","(DURING V-TRIGGER WITH SPECIAL EX MOVE)","6","+","K"],"frame":["12","5","19","D","-2","","","VS*","80","70","","High","","","VS* VS*"]},{"name":["Turn Punch (Lv1)","P","OR","K","(HOLD ANY TWO BUTTONS AND RELEASE)"],"frame":["30","2","22","2","-2","15","12","CA V VS*","80","150","20 / 40","High","","","VS* VS*"]},{"name":["Turn Punch (Lv2)","P","OR","K","(HOLD ANY TWO BUTTONS AND RELEASE)"],"frame":["30","2","22","2","-2","16","12","CA V VS*","100","150","20 / 40","High","","","VS* VS*"]},{"name":["Turn Punch (Lv3)","P","OR","K","(HOLD ANY TWO BUTTONS AND RELEASE)"],"frame":["30","2","22","2","-2","17","12","CA V VS*","120","150","20 / 40","High","","","VS* VS*"]},{"name":["Turn Punch (Lv4)","P","OR","K","(HOLD ANY TWO BUTTONS AND RELEASE)"],"frame":["30","2","22","D","-2","D","12","CA V VS*","140","200","20 / 40","High","","","VS* VS*"]},{"name":["Turn Punch (Lv5)","P","OR","K","(HOLD ANY TWO BUTTONS AND RELEASE)"],"frame":["30","2","22","D","-2","D","12","CA V VS*","160","200","20 / 40","High","","","VS* VS*"]},{"name":["Turn Punch (Lv6)","P","OR","K","(HOLD ANY TWO BUTTONS AND RELEASE)"],"frame":["30","2","22","D","-2","D","12","CA V VS*","180","200","20 / 40","High","","","VS* VS*"]},{"name":["Turn Punch (Lv7)","P","OR","K","(HOLD ANY TWO BUTTONS AND RELEASE)"],"frame":["30","2","22","D","-2","D","12","CA V VS*","210","300","20 / 40","High","","","VS* VS*"]},{"name":["Turn Punch (Lv8)","P","OR","K","(HOLD ANY TWO BUTTONS AND RELEASE)"],"frame":["30","2","22","D","-2","D","12","CA V VS*","240","300","20 / 40","High","","","VS* VS*"]},{"name":["Turn Punch (Lv9)","P","OR","K","(HOLD ANY TWO BUTTONS AND RELEASE)"],"frame":["30","2","22","D","-2","D","12","CA V VS*","270","300","20 / 40","High","","","VS* VS*"]},{"name":["Turn Punch (FINAL)","P","OR","K","(HOLD ANY TWO BUTTONS AND RELEASE)"],"frame":["30","2","22","D","7","D","21","CA V VS*","350","400","20 / 40","High","","","VS* VS*"]},{"name":["Gigaton Blow","236","236","+","P"],"frame":["1+7","10","60","D","-45","","","","330","0","-900 / 0","High","","","14F - 17F projectile invincibility\n11F - 13F projectile & throw invincibility\n1F - 10F full invincibility"]}],"vt2":[{"name":["Standing LP","LP"],"frame":["4","2","7","5","3","4","2","S CA V","30","70","0 / 20","High","","",""]},{"name":["Standing MP","MP"],"frame":["5","4","13","2","0","11","9","S CA V","70","100","0 / 30","High","","",""]},{"name":["Standing HP","HP"],"frame":["12","2","19","0","-3","7","4","CA V","80","150","0 / 50","High","","","Triggers Crush Counter  (D)"]},{"name":["Standing LK","LK"],"frame":["3","2","8","2","1","4","3","V","30","70","0 / 20","High","","",""]},{"name":["Standing MK","MK"],"frame":["6","3","12","5","2","12","9","S CA V","60","100","0 / 30","High","","",""]},{"name":["Standing HK","HK"],"frame":["9","3","18","7","3","15","11","V","80","150","0 / 50","High","","","Triggers Crush Counter (+23F)"]},{"name":["Crouching LP","(WHILE CROUCHING)","LP"],"frame":["4","3","7","4","3","5","4","S CA V","30","70","0 / 20","High","","","Can be rapid canceled"]},{"name":["Crouching MP","(WHILE CROUCHING)","MP"],"frame":["6","3","12","4","2","11","9","S CA V","60","100","0 / 30","High","","",""]},{"name":["Crouching HP","(WHILE CROUCHING)","HP"],"frame":["8","5","22","-1","-5","11","7","S CA V","90(*80)","150","0 / 50","High","","","*"]},{"name":["Crouching LK","(WHILE CROUCHING)","LK"],"frame":["4","3","8","4","1","7","4","V","20","70","0 / 20","Low","","",""]},{"name":["Crouching MK","(WHILE CROUCHING)","MK"],"frame":["7","2","17","2","-2","13","9","V","60","100","0 / 30","Low","","",""]},{"name":["Crouching HK","(WHILE CROUCHING)","HK"],"frame":["8","2","26","D","-14","D","6","V","100","150","0 / 50","Low","","","Triggers Crush Counter  (D)"]},{"name":["Jumping LP","(DURING JUMP)","LP"],"frame":["4","6","","","","","","","40","70","0 / 20","Mid","","",""]},{"name":["Jumping MP","(DURING JUMP)","MP"],"frame":["5","3","","","","","","","70","100","0 / 30","Mid","","",""]},{"name":["Jumping HP","(DURING JUMP)","HP"],"frame":["7","4","","","","","","","90","150","0 / 50","Mid","","",""]},{"name":["Jumping LK","(DURING JUMP)","LK"],"frame":["3","5","","","","","","","40","70","0 / 20","Mid","","",""]},{"name":["Jumping MK","(DURING JUMP)","MK"],"frame":["6","5","","","","","","","70","100","0 / 30","Mid","","",""]},{"name":["Jumping HK","(DURING JUMP)","HK"],"frame":["9","4","","","","","","","90","150","0 / 50","Mid","","",""]},{"name":["Hard Smasher (2)","MK",".","MP"],"frame":["6","4","20","D","-8","D","7","V","40","80","0 / 40","High","","",""]},{"name":["Hard Smasher (3)","(WHEN SELECTING VSKILL I)","MK",".","MP",".","MP","MK"],"frame":["","","31 total frames","","","","","","","","","","","",""]},{"name":["Hard Smasher (4)","(WHEN SELECTING VSKILL I)","MK",".","MP",".","MP","MK",".","P"],"frame":["21","2","23","D","-8","D","9","V","60","120","V-Gauge 0 / 125","High","","",""]},{"name":["Hard Pressure (4)","(WHEN SELECTING VSKILL I)","MK",".","MP",".","MP","MK",".","K"],"frame":["26","3","21","D","-8","D","8","V","60","120","V-Gauge 0 / 125","Mid","","",""]},{"name":["OTB","(WHEN SELECTING VSKILL II)","MK",".","MP",".","MP","MK"],"frame":["","","50 total frames","","","","","","","","","","","",""]},{"name":["Under Impact (2)","LK",".","MK"],"frame":["6","3","16","1","-7","12","4","S* V","40","70","0 / 40","High","","","S*"]},{"name":["Under Impact (3)","LK",".","MK",".","HK"],"frame":["9","2","21","D","-8","D","7","V","70","100","0 / 60","High","","",""]},{"name":["Stomping Combo (2)","(WHILE CROUCHING)","MK",".","2","+","MK"],"frame":["9","2","20","2","-7","7","-2","S* V","40","80","0 / 40","Low","","","S*"]},{"name":["Dirty Bomber","(NEAR OPPONENT)","6","OR","5","+","LP","LK"],"frame":["5","3","17","D","","","","","140","150","0 / 70","Throw","","",""]},{"name":["Dirty Shot","(NEAR OPPONENT)","4","+","LP","LK"],"frame":["5","3","17","D","","","","","130","200","0 / 100","Throw","","",""]},{"name":["[VS1] KKB","(WHEN SELECTING VSKILL I)","MP","MK"],"frame":["","","29 total frames","","","","","","","","","","","","4F - 22F  projectile invincibility"]},{"name":["[VS1] KKB (Cancel)","(WHEN SELECTING VSKILL I)","MP","MK"],"frame":["","","25 total frames","","","","","","","","","","","","4F - 22F  projectile invincibility"]},{"name":["[VS1] Buffalo Swing","(WHEN SELECTING VSKILL I)","(DURING KKB)","P"],"frame":["7","2","21","2","-4","17","11","V","60","100","V-Gauge 0 / 80","High","","","1F - 5F  projectile invincibility"]},{"name":["[VS1] Buffalo Pressure","(WHEN SELECTING VSKILL I)","(DURING KKB)","K"],"frame":["17","3","19","5","-7","19","7","V","50","100","V-Gauge 0 / 100","Mid","","","1F - 14F  projectile invincibility"]},{"name":["[VS2] FFB","(WHEN SELECTING VSKILL II)","MP","MK"],"frame":["","","50 total frames","","","","","","","","","","","","発動後一回だけダッシュストレート・チャージングバッファローの性質変化\n（VT1中のラッシュ時はすべてのストレートが強化される）"]},{"name":["No Mercy","HP","HK"],"frame":["1","","7","","","","","","","","V-Gauge -600 / 0","","","","V-Gauge Timer + 2000F\n                                                                                                                                                                                Gains the special move B3 while active"]},{"name":["Buffalo Headbutt","(DURING GUARD)","6","+","LP","M","H"],"frame":["17","3","23","D","-2","","","","60","0","V-Gauge -300 / 0","High","","18F - 31F","1F - 30F  attack & projectile invincibility\n                                                Recover 200 stun upon activation"]},{"name":["L Dash Straight","c4","6","+","LP"],"frame":["*","4","22","2","-4","","","CA VS*","80","150","10 / 20","High","","","* VS* VS*"]},{"name":["M Dash Straight","c4","6","+","MP"],"frame":["*","4","22","3","-6","","","CA VS*","90","150","10 / 20","High","","","* VS* VS*"]},{"name":["H Dash Straight","c4","6","+","HP"],"frame":["*","4","22","2","-7","","","CA VS*","100","150","10 / 20","High","","","* VS* VS*"]},{"name":["L Dash Straight (VS2 Ver.)","(DURING V-SKILL II)","c4","6","+","LP"],"frame":["*","4","22","D","2","","","CA","90","100","V-Gauge 20 / 40\n\n                10 / 20","High","","","*"]},{"name":["M Dash Straight (VS2 Ver.)","(DURING V-SKILL II)","c4","6","+","MP"],"frame":["*","4","22","D","2","","","CA","100","100","V-Gauge 20 / 40\n\n                10 / 20","High","","","*"]},{"name":["H Dash Straight (VS2 Ver.)","(DURING V-SKILL II)","c4","6","+","HP"],"frame":["*","4","22","D","2","","","CA","110","100","V-Gauge 20 / 40\n\n                10 / 20","High","","","*"]},{"name":["EX Dash Straight","c4","6","+","P","P"],"frame":["*","6","29","D","1","","","V VS*","150","200","-300 / 0","High","","","* VS*"]},{"name":["EX Dash Straight (VS2 Ver.)","(DURING V-SKILL II)","c4","6","+","P","P"],"frame":["*","6","29","D","4","10/D","5","V","160","120","V-Gauge 20 / 60\n\n                -300 / 0","High","","","*"]},{"name":["L Dash Grand Blow","c4","6","+","LK"],"frame":["17","2","26","D","-7","","","VS*","70","150","20 / 40","Low","","","* VS* VS*"]},{"name":["M Dash Grand Blow","c4","6","+","MK"],"frame":["*","2","26","D","-7","","","VS*","80","150","20 / 40","Low","","","* VS* VS*"]},{"name":["H Dash Grand Blow","c4","6","+","HK"],"frame":["*","2","26","D","-7","","","VS*","90","150","20 / 40","Low","","","* VS* VS*"]},{"name":["EX Dash Grand Blow","c4","6","+","K","K"],"frame":["*","2","23","D","-2","D","5","V VS*","140","200","-300 / 0","Low","","","* VS* VS*"]},{"name":["L Screw Smash","623","+","LK"],"frame":["10","5","25","D","-10","","","CA","100","150","20 / 40","High","","","Will not hit crouching opponents"]},{"name":["M Screw Smash","623","+","MK"],"frame":["13","5","26","D","-10","","","CA","100","150","20 / 40","High","","","Will not hit crouching opponents"]},{"name":["H Screw Smash","623","+","HK"],"frame":["23","5","23","D","-10","","","CA","100","150","20 / 40","High","","","Will not hit crouching opponents"]},{"name":["EX Screw Smash","623","+","K","K"],"frame":["12","5","29","D","-17","D","-10","V","160","200","-300 / 0","High","","","Armor from 3F to 16F"]},{"name":["Turn Punch (Lv1)","P","OR","K","(HOLD ANY TWO BUTTONS AND RELEASE)"],"frame":["30","2","22","2","-2","","","CA VS*","80","150","20 / 40","High","","","VS* VS*"]},{"name":["Turn Punch (Lv2)","P","OR","K","(HOLD ANY TWO BUTTONS AND RELEASE)"],"frame":["30","2","22","2","-2","","","CA VS*","100","150","20 / 40","High","","","VS* VS*"]},{"name":["Turn Punch (Lv3)","P","OR","K","(HOLD ANY TWO BUTTONS AND RELEASE)"],"frame":["30","2","22","2","-2","","","CA VS*","120","150","20 / 40","High","","","VS* VS*"]},{"name":["Turn Punch (Lv4)","P","OR","K","(HOLD ANY TWO BUTTONS AND RELEASE)"],"frame":["30","2","22","D","-2","","","CA VS*","140","200","20 / 40","High","","","VS* VS*"]},{"name":["Turn Punch (Lv5)","P","OR","K","(HOLD ANY TWO BUTTONS AND RELEASE)"],"frame":["30","2","22","D","-2","","","CA VS*","160","200","20 / 40","High","","","VS* VS*"]},{"name":["Turn Punch (Lv6)","P","OR","K","(HOLD ANY TWO BUTTONS AND RELEASE)"],"frame":["30","2","22","D","-2","","","CA VS*","180","200","20 / 40","High","","","VS* VS*"]},{"name":["Turn Punch (Lv7)","P","OR","K","(HOLD ANY TWO BUTTONS AND RELEASE)"],"frame":["30","2","22","D","-2","","","CA VS*","210","300","20 / 40","High","","","VS* VS*"]},{"name":["Turn Punch (Lv8)","P","OR","K","(HOLD ANY TWO BUTTONS AND RELEASE)"],"frame":["30","2","22","D","-2","","","CA VS*","240","300","20 / 40","High","","","VS* VS*"]},{"name":["Turn Punch (Lv9)","P","OR","K","(HOLD ANY TWO BUTTONS AND RELEASE)"],"frame":["30","2","22","D","-2","","","CA VS*","270","300","20 / 40","High","","","VS* VS*"]},{"name":["Turn Punch (FINAL)","P","OR","K","(HOLD ANY TWO BUTTONS AND RELEASE)"],"frame":["30","2","22","D","7","","","CA VS*","350","400","20 / 40","High","","","VS* VS*"]},{"name":["[VT] B3","(DURING V-TRIGGER II)","HP","HK"],"frame":["7","2","60","D","","","","","180","350","0 / 80","Throw","","","Uses 600F V-Gauge Timer\n                                                                                                                                                                                Uses an additional 400F of V-Timer gauge on successful hit\nWhen performed as a throw cancel, it can throw an opponent in hit stun"]},{"name":["Gigaton Blow","236","236","+","P"],"frame":["1+7","10","60","D","-45","","","","330","0","-900 / 0","High","","","14F - 17F  projectile invincibility\n11F - 13F  projectile & throw invincibility\n1F - 10F  full invincibility"]}]}